Metadata-Version: 2.1
Name: POSTagger
Version: 0.1.13b0
Summary: A GUI app for semi-automatic POS tagging
Home-page: https://github.com/asdoost/POSTagger
Author: Abbas Safardoost
Author-email: a.safardoust@gmail.com
License: MIT
Download-URL: https://github.com/asdoost/POSTagger/archive/refs/tags/v0.1.13-beta.tar.gz
Keywords: POS Tagger,Part of Speech Tagger
Platform: UNKNOWN
Classifier: Development Status :: 4 - Beta
Classifier: Topic :: Text Processing :: Linguistic
Classifier: License :: OSI Approved :: MIT License
Classifier: Operating System :: Unix
Classifier: Operating System :: Microsoft :: Windows
Classifier: Programming Language :: Python :: 3.6
License-File: LICENSE
